arcas_analyzer/ContextClasses.py
arcas_analyzer/__init__.py
arcas_analyzer/arcas_analyzer.sh
arcas_analyzer/cli.py
arcas_analyzer/launcher.py
arcas_analyzer/lib_parser.py
arcas_analyzer/main.py
arcas_analyzer/monitor.py
arcas_analyzer/parser.py
arcas_analyzer/utility.py
arcas_analyzer-0.1.2.dist-info/METADATA
arcas_analyzer-0.1.2.dist-info/WHEEL
arcas_analyzer-0.1.2.dist-info/entry_points.txt
arcas_analyzer-0.1.2.dist-info/top_level.txt
arcas_analyzer-0.1.2.dist-info/RECORD
