Metadata-Version: 2.4
Name: arcas_analyzer
Version: 0.1.2
Summary: Analyzer project for Verilog/OpenCores
Author: Sudheer
Requires-Python: >=3.8
Requires-Dist: pyslang>=8.1.0
Requires-Dist: psutil
